{"ARI":{ "sacks_earned":"0.3333","sacks_allowed":"2"},"ATL":{ "sacks_earned":"4","sacks_allowed":"1"},"BAL":{ "sacks_earned":"2.6667","sacks_allowed":"2"},"BUF":{ "sacks_earned":"3.6667","sacks_allowed":"1"},"CAR":{ "sacks_earned":"1.3333","sacks_allowed":"3.6667"},"CHI":{ "sacks_earned":"2.6667","sacks_allowed":"2.3333"},"CIN":{ "sacks_earned":"2","sacks_allowed":"4.6667"},"CLE":{ "sacks_earned":"2.6667","sacks_allowed":"2"},"DAL":{ "sacks_earned":"1","sacks_allowed":"3.3333"},"DEN":{ "sacks_earned":"1.6667","sacks_allowed":"3"},"DET":{ "sacks_earned":"3","sacks_allowed":"1.3333"},"GB":{ "sacks_earned":"3.6667","sacks_allowed":"1"},"HOU":{ "sacks_earned":"4.6667","sacks_allowed":"2.6667"},"IND":{ "sacks_earned":"2.3333","sacks_allowed":"3.3333"},"JAX":{ "sacks_earned":"3.6667","sacks_allowed":"2.6667"},"KC":{ "sacks_earned":"4","sacks_allowed":"3"},"LA":{ "sacks_earned":"3","sacks_allowed":"2.6667"},"LAC":{ "sacks_earned":"1.3333","sacks_allowed":"3"},"LV":{ "sacks_earned":"2.6667","sacks_allowed":"1.6667"},"MIA":{ "sacks_earned":"3.6667","sacks_allowed":"2.3333"},"MIN":{ "sacks_earned":"2","sacks_allowed":"3.6667"},"NE":{ "sacks_earned":"3","sacks_allowed":"3"},"NO":{ "sacks_earned":"3.3333","sacks_allowed":"1.3333"},"NYG":{ "sacks_earned":"2","sacks_allowed":"4.6667"},"NYJ":{ "sacks_earned":"1.6667","sacks_allowed":"2.6667"},"PHI":{ "sacks_earned":"1.3333","sacks_allowed":"0.3333"},"PIT":{ "sacks_earned":"2.3333","sacks_allowed":"2"},"SEA":{ "sacks_earned":"2.3333","sacks_allowed":"2"},"SF":{ "sacks_earned":"2","sacks_allowed":"1.6667"},"TB":{ "sacks_earned":"2.3333","sacks_allowed":"3"},"TEN":{ "sacks_earned":"2.6667","sacks_allowed":"6.3333"},"WAS":{ "sacks_earned":"1.3333","sacks_allowed":"1"}}
